./.gitignore
./PKG-INFO
./README.md
./pyproject.toml
./vision_agents/plugins/vogent/__init__.py
./vision_agents/plugins/vogent/vogent_turn_detection.py
vision_agents/plugins/vogent/__init__.py
vision_agents/plugins/vogent/vogent_turn_detection.py
vision_agents_plugins_vogent-0.2.10.dist-info/METADATA
vision_agents_plugins_vogent-0.2.10.dist-info/WHEEL
vision_agents_plugins_vogent-0.2.10.dist-info/RECORD
